hsnf/Z_module.py
hsnf/__init__.py
hsnf/integer_system.py
hsnf/lattice.py
hsnf/py.typed
hsnf/utils.py
hsnf-0.3.16.dist-info/LICENSE
hsnf-0.3.16.dist-info/METADATA
hsnf-0.3.16.dist-info/WHEEL
hsnf-0.3.16.dist-info/top_level.txt
hsnf-0.3.16.dist-info/RECORD
